pympls/__init__.py
pympls-0.0.1.dist-info/LICENSE
pympls-0.0.1.dist-info/METADATA
pympls-0.0.1.dist-info/WHEEL
pympls-0.0.1.dist-info/top_level.txt
pympls-0.0.1.dist-info/RECORD
