Metadata-Version: 2.1
Name: pympls
Version: 0.0.1
Summary: A Python Parser for Blu-ray's MPLS Playlist files
Home-page: https://github.com/rlaPHOENiX/pympls
Author: PHOENiX
Author-email: rlaphoenix@pm.me
License: MIT
Platform: UNKNOWN
Classifier: Programming Language :: Python :: 3
Classifier: License :: OSI Approved :: MIT License
Classifier: Operating System :: OS Independent
Requires-Python: >=3.6
